loove_credentials/__init__.py
loove_credentials/__main__.py
loove_credentials/agent_provider.py
loove_credentials/cli.py
loove_credentials/env_credential_manager.py
loove_credentials/github_app_auth.py
loove_credentials/shopify_client.py
loove_credentials/shopify_provider.py
loove_credentials-1.2.0.dist-info/METADATA
loove_credentials-1.2.0.dist-info/WHEEL
loove_credentials-1.2.0.dist-info/top_level.txt
loove_credentials-1.2.0.dist-info/RECORD
