Metadata-Version: 2.4
Name: loove-credentials
Version: 1.2.0
Summary: Credential provider for LOOVE AI agents
Requires-Python: >=3.9
Requires-Dist: PyJWT>=2.0.0
Requires-Dist: requests>=2.25.0
Requires-Dist: cryptography>=3.4.0
Provides-Extra: dev
Requires-Dist: build; extra == "dev"
Requires-Dist: twine; extra == "dev"
